{
  "composite": {
    "score": 54,
    "label": "Neutral",
    "color": "#f6ad55",
    "components": {
      "vix": {
        "value": 19.72,
        "score": 60,
        "contribution": 2.0,
        "interpretation": "Calm"
      },
      "eurusd": {
        "value": 1.1686,
        "chg_pct": -0.2,
        "score": 50,
        "contribution": 0.0,
        "interpretation": "Neutral"
      },
      "stoxx50": {
        "value": 5858.8501,
        "ma50": 5851.754,
        "pct_from_ma": 0.12,
        "above_ma50": true,
        "score": 55,
        "contribution": 1.2,
        "interpretation": "Uptrend"
      },
      "dax": {
        "value": 24062.2207,
        "ma50": 23939.7222,
        "pct_from_ma": 0.51,
        "above_ma50": true,
        "score": 55,
        "contribution": 0.8,
        "interpretation": "Uptrend"
      }
    }
  },
  "indicators": {
    "vstoxx": {
      "ticker": "V2TX.DE",
      "label": "VSTOXX",
      "error": "'PriceHistory' object has no attribute '_dividends'"
    },
    "vix": {
      "ticker": "^VIX",
      "label": "VIX",
      "price": 19.72,
      "prev": 18.91,
      "chg_pct": 4.28,
      "ma50": 22.4922,
      "above_ma50": false
    },
    "eurusd": {
      "ticker": "EURUSD=X",
      "label": "EUR/USD",
      "price": 1.1686,
      "prev": 1.171,
      "chg_pct": -0.2,
      "ma50": 1.1662,
      "above_ma50": true
    },
    "stoxx50": {
      "ticker": "^STOXX50E",
      "label": "Euro Stoxx 50",
      "price": 5858.8501,
      "prev": 5910.8599,
      "chg_pct": -0.88,
      "ma50": 5851.754,
      "above_ma50": true
    },
    "dax": {
      "ticker": "^GDAXI",
      "label": "DAX",
      "price": 24062.2207,
      "prev": 24210.0898,
      "chg_pct": -0.61,
      "ma50": 23939.7222,
      "above_ma50": true
    }
  },
  "updated": "2026-04-23T10:41:31.721343"
}