{
  "composite": {
    "score": 36,
    "label": "Fear",
    "color": "#f56565",
    "components": {
      "vstoxx": {
        "value": 35.457,
        "score": 20,
        "contribution": -7.5,
        "interpretation": "High fear"
      },
      "vix": {
        "value": 24.67,
        "score": 50,
        "contribution": 0.0,
        "interpretation": "Neutral"
      },
      "eurusd": {
        "value": 1.1547,
        "chg_pct": 0.22,
        "score": 50,
        "contribution": 0.0,
        "interpretation": "Neutral"
      },
      "stoxx50": {
        "value": 5692.8599,
        "ma50": 5867.939,
        "pct_from_ma": -2.98,
        "above_ma50": false,
        "score": 35,
        "contribution": -3.8,
        "interpretation": "Downtrend"
      },
      "dax": {
        "value": 23168.0801,
        "ma50": 24130.2594,
        "pct_from_ma": -3.99,
        "above_ma50": false,
        "score": 35,
        "contribution": -2.2,
        "interpretation": "Downtrend"
      }
    }
  },
  "indicators": {
    "vstoxx": {
      "ticker": "V2TX.DE",
      "label": "VSTOXX",
      "price": 35.457,
      "prev": 35.457,
      "chg_pct": 0.0,
      "ma50": null,
      "above_ma50": null
    },
    "vix": {
      "ticker": "^VIX",
      "label": "VIX",
      "price": 24.67,
      "prev": 23.9,
      "chg_pct": 3.22,
      "ma50": 22.0204,
      "above_ma50": true
    },
    "eurusd": {
      "ticker": "EURUSD=X",
      "label": "EUR/USD",
      "price": 1.1547,
      "prev": 1.1522,
      "chg_pct": 0.22,
      "ma50": 1.1702,
      "above_ma50": false
    },
    "stoxx50": {
      "ticker": "^STOXX50E",
      "label": "Euro Stoxx 50",
      "price": 5692.8599,
      "prev": 5723.6802,
      "chg_pct": -0.54,
      "ma50": 5867.939,
      "above_ma50": false
    },
    "dax": {
      "ticker": "^GDAXI",
      "label": "DAX",
      "price": 23168.0801,
      "prev": 23298.89,
      "chg_pct": -0.56,
      "ma50": 24130.2594,
      "above_ma50": false
    }
  },
  "updated": "2026-04-06T17:33:26.780985"
}