{
  "stocks": [
    {
      "ticker": "MSFT",
      "name": "Microsoft Corporation",
      "price_native": 407.78,
      "prev_close": 408.651,
      "currency": "USD",
      "change_pct": -0.21,
      "price_eur": 347.31,
      "prev_eur": 348.05,
      "sector": "Technology",
      "country": "United States",
      "pe_ratio": 24.27262,
      "beta": 1.107,
      "eps_ttm": 16.8,
      "dividend_yield": 0.89,
      "market_cap": 3029167243264,
      "pb_ratio": 7.750261,
      "ps_ratio": 9.517512,
      "roe": 0.34013999,
      "roa": 0.14814,
      "debt_to_equity": 30.271,
      "current_ratio": 1.283,
      "profit_margin": 0.39341998,
      "revenue_growth": 0.183,
      "earnings_growth": 0.234,
      "recommendation": "buy",
      "analyst_total": 54,
      "analyst_target_mean": 486.08,
      "analyst_target_high": 621.74,
      "analyst_target_low": 333.87,
      "52w_high": 473.08,
      "52w_low": 303.44,
      "timestamp": "2026-05-01T09:19:49.243557",
      "shares": 5,
      "value_eur": 1736.55
    },
    {
      "ticker": "ENR.DE",
      "name": "Siemens Energy AG             N",
      "price_native": 180.58,
      "prev_close": 175.26,
      "currency": "EUR",
      "change_pct": 3.04,
      "price_eur": 180.58,
      "prev_eur": 175.26,
      "sector": "Industrials",
      "country": "Germany",
      "pe_ratio": 83.99069,
      "beta": 1.809,
      "eps_ttm": 2.15,
      "dividend_yield": 0.39,
      "market_cap": 154458062848,
      "pb_ratio": 13.717715,
      "ps_ratio": 3.8798811,
      "roe": 0.20254,
      "roa": 0.023,
      "debt_to_equity": 33.02,
      "current_ratio": 0.924,
      "profit_margin": 0.04755,
      "revenue_growth": 0.082,
      "earnings_growth": 2.405,
      "recommendation": "buy",
      "analyst_total": 25,
      "analyst_target_mean": 178.68,
      "analyst_target_high": 250.0,
      "analyst_target_low": 100.0,
      "52w_high": 191.66,
      "52w_low": 70.0,
      "timestamp": "2026-05-01T09:19:49.518226",
      "shares": 9,
      "value_eur": 1625.22
    },
    {
      "ticker": "VH2.DE",
      "name": "Friedrich Vorwerk Group SE    I",
      "price_native": 72.95,
      "prev_close": 71.5,
      "currency": "EUR",
      "change_pct": 2.03,
      "price_eur": 72.95,
      "prev_eur": 71.5,
      "sector": "Industrials",
      "country": "Germany",
      "pe_ratio": 20.607344,
      "beta": 0.876,
      "eps_ttm": 3.54,
      "dividend_yield": 0.96,
      "market_cap": 1458999936,
      "pb_ratio": 5.7018914,
      "ps_ratio": 2.0662475,
      "roe": 0.39021,
      "roa": 0.14071,
      "debt_to_equity": 9.819,
      "current_ratio": 1.843,
      "profit_margin": 0.1225,
      "revenue_growth": 0.257,
      "earnings_growth": 1.161,
      "recommendation": "hold",
      "analyst_total": 4,
      "analyst_target_mean": 86.5,
      "analyst_target_high": 111.0,
      "analyst_target_low": 60.0,
      "52w_high": 109.2,
      "52w_low": 54.6,
      "timestamp": "2026-05-01T09:19:49.948194",
      "shares": 11,
      "value_eur": 802.45
    },
    {
      "ticker": "MILDEF.ST",
      "name": "Mildef Group AB",
      "price_native": 173.1,
      "prev_close": 173.5,
      "currency": "SEK",
      "change_pct": -0.23,
      "price_eur": 15.88,
      "prev_eur": 15.92,
      "sector": "Industrials",
      "country": "Sweden",
      "pe_ratio": 37.145924,
      "beta": 1.012,
      "eps_ttm": 4.66,
      "dividend_yield": 0.43,
      "market_cap": 8152126976,
      "pb_ratio": 5.050476,
      "ps_ratio": 3.37772,
      "roe": 0.1449,
      "roa": 0.06657,
      "debt_to_equity": 43.807,
      "current_ratio": 2.091,
      "profit_margin": 0.0907,
      "revenue_growth": 1.085,
      "earnings_growth": null,
      "recommendation": "buy",
      "analyst_total": 5,
      "analyst_target_mean": 20.22,
      "analyst_target_high": 22.93,
      "analyst_target_low": 18.53,
      "52w_high": 27.01,
      "52w_low": 10.11,
      "timestamp": "2026-05-01T09:19:50.504906",
      "shares": 60,
      "value_eur": 952.8
    },
    {
      "ticker": "GOOG",
      "name": "Alphabet Inc.",
      "price_native": 381.94,
      "prev_close": 382.45,
      "currency": "USD",
      "change_pct": -0.13,
      "price_eur": 325.3,
      "prev_eur": 325.73,
      "sector": "Communication Services",
      "country": "United States",
      "pe_ratio": 29.155725,
      "beta": 1.128,
      "eps_ttm": 13.1,
      "dividend_yield": 0.24,
      "market_cap": 4620328370176,
      "pb_ratio": 11.118097,
      "ps_ratio": 11.469502,
      "roe": 0.35705003,
      "roa": 0.15427,
      "debt_to_equity": 16.133,
      "current_ratio": 2.005,
      "profit_margin": 0.32810003,
      "revenue_growth": 0.18,
      "earnings_growth": 0.311,
      "recommendation": "buy",
      "analyst_total": 18,
      "analyst_target_mean": 310.02,
      "analyst_target_high": 344.94,
      "analyst_target_low": 157.56,
      "52w_high": 325.89,
      "52w_low": 127.32,
      "timestamp": "2026-05-01T09:19:50.994511",
      "shares": 2,
      "value_eur": 650.6
    },
    {
      "ticker": "AIR.PA",
      "name": "AIRBUS SE",
      "price_native": 174.88,
      "prev_close": 175.32,
      "currency": "EUR",
      "change_pct": -0.25,
      "price_eur": 174.88,
      "prev_eur": 175.32,
      "sector": "Industrials",
      "country": "Netherlands",
      "pe_ratio": 26.537178,
      "beta": 0.878,
      "eps_ttm": 6.59,
      "dividend_yield": 1.83,
      "market_cap": 137670393856,
      "pb_ratio": 5.273983,
      "ps_ratio": 1.8981427,
      "roe": 0.19748,
      "roa": 0.024820002,
      "debt_to_equity": 55.655,
      "current_ratio": 1.14,
      "profit_margin": 0.06913,
      "revenue_growth": -0.066,
      "earnings_growth": -0.265,
      "recommendation": "buy",
      "analyst_total": 23,
      "analyst_target_mean": 209.74,
      "analyst_target_high": 255.0,
      "analyst_target_low": 170.0,
      "52w_high": 221.3,
      "52w_low": 151.28,
      "timestamp": "2026-05-01T09:19:51.345483",
      "shares": 7,
      "value_eur": 1224.16
    },
    {
      "ticker": "NVDA",
      "name": "NVIDIA Corporation",
      "price_native": 199.57,
      "prev_close": 200.0097,
      "currency": "USD",
      "change_pct": -0.22,
      "price_eur": 169.97,
      "prev_eur": 170.35,
      "sector": "Technology",
      "country": "United States",
      "pe_ratio": 40.645622,
      "beta": 2.335,
      "eps_ttm": 4.91,
      "dividend_yield": 0.02,
      "market_cap": 4850548998144,
      "pb_ratio": 30.835909,
      "ps_ratio": 22.462692,
      "roe": 1.01485,
      "roa": 0.51188,
      "debt_to_equity": 7.255,
      "current_ratio": 3.905,
      "profit_margin": 0.55603004,
      "revenue_growth": 0.732,
      "earnings_growth": 0.956,
      "recommendation": "buy",
      "analyst_total": 57,
      "analyst_target_mean": 229.25,
      "analyst_target_high": 323.65,
      "analyst_target_low": 119.24,
      "52w_high": 184.67,
      "52w_low": 94.39,
      "timestamp": "2026-05-01T09:19:51.747791",
      "shares": 0,
      "value_eur": 0.0
    },
    {
      "ticker": "MU",
      "name": "Micron Technology, Inc.",
      "price_native": 517.16,
      "prev_close": 505.0,
      "currency": "USD",
      "change_pct": 2.41,
      "price_eur": 440.47,
      "prev_eur": 430.11,
      "sector": "Technology",
      "country": "United States",
      "pe_ratio": 24.394337,
      "beta": 1.606,
      "eps_ttm": 21.2,
      "dividend_yield": 0.12,
      "market_cap": 583218888704,
      "pb_ratio": 8.050812,
      "ps_ratio": 10.034909,
      "roe": 0.39823002,
      "roa": 0.20145,
      "debt_to_equity": 14.902,
      "current_ratio": 2.897,
      "profit_margin": 0.41486,
      "revenue_growth": 1.963,
      "earnings_growth": 7.56,
      "recommendation": "buy",
      "analyst_total": 42,
      "analyst_target_mean": 469.63,
      "analyst_target_high": 851.7,
      "analyst_target_low": 212.07,
      "52w_high": 456.09,
      "52w_low": 66.89,
      "timestamp": "2026-05-01T09:19:52.080988",
      "shares": 1,
      "value_eur": 440.47
    },
    {
      "ticker": "BTC-USD",
      "name": "Bitcoin USD",
      "price_native": 77316.0938,
      "prev_close": 76296.7266,
      "currency": "USD",
      "change_pct": 1.34,
      "price_eur": 65850.12,
      "prev_eur": 64981.92,
      "sector": "",
      "country": "",
      "pe_ratio": null,
      "beta": null,
      "eps_ttm": null,
      "dividend_yield": null,
      "market_cap": 1547854807040,
      "pb_ratio": null,
      "ps_ratio": null,
      "roe": null,
      "roa": null,
      "debt_to_equity": null,
      "current_ratio": null,
      "profit_margin": null,
      "revenue_growth": null,
      "earnings_growth": null,
      "analyst_total": 0,
      "52w_high": 107482.9,
      "52w_low": 51165.2,
      "timestamp": "2026-05-01T09:19:52.551325",
      "shares": 0,
      "value_eur": 0.0
    },
    {
      "ticker": "GC=F",
      "name": "Gold Jun 26",
      "price_native": 4577.2998,
      "prev_close": 4638.6001,
      "currency": "USD",
      "change_pct": -1.32,
      "price_eur": 3898.49,
      "prev_eur": 3950.7,
      "sector": "",
      "country": "",
      "pe_ratio": null,
      "beta": null,
      "eps_ttm": null,
      "dividend_yield": null,
      "market_cap": null,
      "pb_ratio": null,
      "ps_ratio": null,
      "roe": null,
      "roa": null,
      "debt_to_equity": null,
      "current_ratio": null,
      "profit_margin": null,
      "revenue_growth": null,
      "earnings_growth": null,
      "analyst_total": 0,
      "52w_high": 4757.77,
      "52w_low": 2661.56,
      "timestamp": "2026-05-01T09:19:52.829947",
      "shares": 0,
      "value_eur": 0.0
    },
    {
      "ticker": "SI=F",
      "name": "Silver May 26",
      "price_native": 73.53,
      "prev_close": 74.8,
      "currency": "USD",
      "change_pct": -1.7,
      "price_eur": 62.63,
      "prev_eur": 63.71,
      "sector": "",
      "country": "",
      "pe_ratio": null,
      "beta": null,
      "eps_ttm": null,
      "dividend_yield": null,
      "market_cap": null,
      "pb_ratio": null,
      "ps_ratio": null,
      "roe": null,
      "roa": null,
      "debt_to_equity": null,
      "current_ratio": null,
      "profit_margin": null,
      "revenue_growth": null,
      "earnings_growth": null,
      "analyst_total": 0,
      "52w_high": 103.31,
      "52w_low": 27.18,
      "timestamp": "2026-05-01T09:19:53.157755",
      "shares": 0,
      "value_eur": 0.0
    },
    {
      "ticker": "AMZN",
      "name": "Amazon.com, Inc.",
      "price_native": 265.06,
      "prev_close": 264.06,
      "currency": "USD",
      "change_pct": 0.38,
      "price_eur": 225.75,
      "prev_eur": 224.9,
      "sector": "Consumer Cyclical",
      "country": "United States",
      "pe_ratio": 31.743711,
      "beta": 1.383,
      "eps_ttm": 8.35,
      "dividend_yield": null,
      "market_cap": 2850521874432,
      "pb_ratio": 6.919543,
      "ps_ratio": 3.9760447,
      "roe": 0.22286,
      "roa": 0.06928,
      "debt_to_equity": 43.435,
      "current_ratio": 1.051,
      "profit_margin": 0.108339995,
      "revenue_growth": 0.136,
      "earnings_growth": 0.05,
      "recommendation": "buy",
      "analyst_total": 64,
      "analyst_target_mean": 241.86,
      "analyst_target_high": 306.61,
      "analyst_target_low": 149.05,
      "52w_high": 233.26,
      "52w_low": 156.59,
      "timestamp": "2026-05-01T09:19:53.444067",
      "shares": 0,
      "value_eur": 0.0
    },
    {
      "ticker": "HO.PA",
      "name": "THALES",
      "price_native": 233.9,
      "prev_close": 229.5,
      "currency": "EUR",
      "change_pct": 1.92,
      "price_eur": 233.9,
      "prev_eur": 229.5,
      "sector": "Industrials",
      "country": "France",
      "pe_ratio": 28.734642,
      "beta": 0.151,
      "eps_ttm": 8.14,
      "dividend_yield": 1.67,
      "market_cap": 48065417216,
      "pb_ratio": 6.0314593,
      "ps_ratio": 2.1713295,
      "roe": 0.21103,
      "roa": 0.03435,
      "debt_to_equity": 76.737,
      "current_ratio": 0.845,
      "profit_margin": 0.07564,
      "revenue_growth": 0.071,
      "earnings_growth": 1.512,
      "recommendation": "buy",
      "analyst_total": 18,
      "analyst_target_mean": 294.44,
      "analyst_target_high": 390.0,
      "analyst_target_low": 250.0,
      "52w_high": 279.3,
      "52w_low": 216.2,
      "timestamp": "2026-05-01T09:19:53.808430",
      "shares": 0,
      "value_eur": 0.0
    },
    {
      "ticker": "AAPL",
      "name": "Apple Inc.",
      "price_native": 271.35,
      "prev_close": 276.54,
      "currency": "USD",
      "change_pct": -1.88,
      "price_eur": 231.11,
      "prev_eur": 235.53,
      "sector": "Technology",
      "country": "United States",
      "pe_ratio": 34.348103,
      "beta": null,
      "eps_ttm": 7.9,
      "dividend_yield": 0.38,
      "market_cap": 3983727394816,
      "pb_ratio": 45.24008,
      "ps_ratio": 8.82445,
      "roe": 1.4147099,
      "roa": 0.26229,
      "debt_to_equity": 79.548,
      "current_ratio": 1.07,
      "profit_margin": 0.27152002,
      "revenue_growth": 0.166,
      "earnings_growth": 0.218,
      "recommendation": "buy",
      "analyst_total": 42,
      "analyst_target_mean": 254.19,
      "analyst_target_high": 298.1,
      "analyst_target_low": 183.12,
      "52w_high": 245.82,
      "52w_low": 164.59,
      "timestamp": "2026-05-01T09:19:54.174869",
      "shares": 0,
      "value_eur": 0.0
    },
    {
      "ticker": "LLY",
      "name": "Eli Lilly and Company",
      "price_native": 934.6,
      "prev_close": 933.0,
      "currency": "USD",
      "change_pct": 0.17,
      "price_eur": 796.0,
      "prev_eur": 794.64,
      "sector": "Healthcare",
      "country": "United States",
      "pe_ratio": 33.224316,
      "beta": 0.504,
      "eps_ttm": 28.13,
      "dividend_yield": 0.67,
      "market_cap": 836297687040,
      "pb_ratio": 31.515762,
      "ps_ratio": 11.575214,
      "roe": null,
      "roa": null,
      "debt_to_equity": 165.31,
      "current_ratio": null,
      "profit_margin": 0.34986,
      "revenue_growth": 0.555,
      "earnings_growth": 1.698,
      "recommendation": "buy",
      "analyst_total": 29,
      "analyst_target_mean": 1024.04,
      "analyst_target_high": 1277.55,
      "analyst_target_low": 723.95,
      "52w_high": 965.79,
      "52w_low": 531.27,
      "timestamp": "2026-05-01T09:19:54.608964",
      "shares": 0,
      "value_eur": 0.0
    },
    {
      "ticker": "GBF.DE",
      "name": "Bilfinger SE                  I",
      "price_native": 98.1,
      "prev_close": 97.3,
      "currency": "EUR",
      "change_pct": 0.82,
      "price_eur": 98.1,
      "prev_eur": 97.3,
      "sector": "Industrials",
      "country": "Germany",
      "pe_ratio": 20.872341,
      "beta": 0.58,
      "eps_ttm": 4.7,
      "dividend_yield": 2.85,
      "market_cap": 3623786752,
      "pb_ratio": 2.7211452,
      "ps_ratio": 0.66773295,
      "roe": 0.1381,
      "roa": 0.04932,
      "debt_to_equity": 27.783,
      "current_ratio": 1.252,
      "profit_margin": 0.03243,
      "revenue_growth": 0.045,
      "earnings_growth": -0.16,
      "recommendation": "buy",
      "analyst_total": 4,
      "analyst_target_mean": 122.0,
      "analyst_target_high": 132.0,
      "analyst_target_low": 107.0,
      "52w_high": 129.3,
      "52w_low": 70.1,
      "timestamp": "2026-05-01T09:19:55.016322",
      "shares": 0,
      "value_eur": 0.0
    },
    {
      "ticker": "BA.L",
      "name": "BAE SYSTEMS PLC ORD 2.5P",
      "price_native": 2019.0,
      "prev_close": 2034.8101,
      "currency": "GBX",
      "change_pct": -0.78,
      "price_eur": 23.39,
      "prev_eur": 23.57,
      "sector": "Industrials",
      "country": "United Kingdom",
      "pe_ratio": 29.691177,
      "beta": -0.01,
      "eps_ttm": 0.68,
      "dividend_yield": 1.78,
      "market_cap": 59168780288,
      "pb_ratio": 5.12827,
      "ps_ratio": 2.0881133,
      "roe": 0.18141001,
      "roa": 0.045339998,
      "debt_to_equity": 76.728,
      "current_ratio": 0.987,
      "profit_margin": 0.07277,
      "revenue_growth": 0.067,
      "earnings_growth": 0.087,
      "recommendation": "buy",
      "analyst_total": 18,
      "analyst_target_mean": 26.9,
      "analyst_target_high": 30.84,
      "analyst_target_low": 19.69,
      "52w_high": 27.34,
      "52w_low": 18.4,
      "timestamp": "2026-05-01T09:19:55.758805",
      "shares": 0,
      "value_eur": 0.0
    },
    {
      "ticker": "BESI.AS",
      "name": "BE Semiconductor Industries N.V",
      "price_native": 247.2,
      "prev_close": 239.5,
      "currency": "EUR",
      "change_pct": 3.22,
      "price_eur": 247.2,
      "prev_eur": 239.5,
      "sector": "Technology",
      "country": "Netherlands",
      "pe_ratio": 130.10527,
      "beta": 1.165,
      "eps_ttm": 1.9,
      "dividend_yield": 0.64,
      "market_cap": 19586367488,
      "pb_ratio": 42.87201,
      "ps_ratio": 30.9879,
      "roe": 0.3127,
      "roa": 0.10138,
      "debt_to_equity": 113.605,
      "current_ratio": 4.735,
      "profit_margin": 0.24002,
      "revenue_growth": 0.283,
      "earnings_growth": 0.635,
      "recommendation": "buy",
      "analyst_total": 22,
      "analyst_target_mean": 242.32,
      "analyst_target_high": 340.0,
      "analyst_target_low": 140.0,
      "52w_high": 257.4,
      "52w_low": 96.28,
      "timestamp": "2026-05-01T09:19:56.119713",
      "shares": 0,
      "value_eur": 0.0
    },
    {
      "ticker": "ASM.AS",
      "name": "ASM International N.V.",
      "price_native": 830.6,
      "prev_close": 807.8,
      "currency": "EUR",
      "change_pct": 2.82,
      "price_eur": 830.6,
      "prev_eur": 807.8,
      "sector": "Technology",
      "country": "Netherlands",
      "pe_ratio": 41.15956,
      "beta": 1.428,
      "eps_ttm": 20.18,
      "dividend_yield": 0.39,
      "market_cap": 40604770304,
      "pb_ratio": 9.468009,
      "ps_ratio": 12.702885,
      "roe": 0.24936001,
      "roa": 0.10936,
      "debt_to_equity": 1.679,
      "current_ratio": 2.245,
      "profit_margin": 0.31006,
      "revenue_growth": 0.028,
      "earnings_growth": null,
      "recommendation": "buy",
      "analyst_total": 20,
      "analyst_target_mean": 918.1,
      "analyst_target_high": 1095.0,
      "analyst_target_low": 639.0,
      "52w_high": 871.2,
      "52w_low": 400.0,
      "timestamp": "2026-05-01T09:19:56.570482",
      "shares": 0,
      "value_eur": 0.0
    },
    {
      "ticker": "CAT",
      "name": "Caterpillar, Inc.",
      "price_native": 890.11,
      "prev_close": 888.55,
      "currency": "USD",
      "change_pct": 0.18,
      "price_eur": 758.11,
      "prev_eur": 756.78,
      "sector": "Industrials",
      "country": "United States",
      "pe_ratio": 44.24006,
      "beta": 1.519,
      "eps_ttm": 20.12,
      "dividend_yield": 0.75,
      "market_cap": 414156881920,
      "pb_ratio": 19.427504,
      "ps_ratio": 6.1275783,
      "roe": 0.43526,
      "roa": 0.07891,
      "debt_to_equity": 206.67,
      "current_ratio": 1.436,
      "profit_margin": 0.13144,
      "revenue_growth": 0.18,
      "earnings_growth": -0.114,
      "recommendation": "buy",
      "analyst_total": 26,
      "analyst_target_mean": 657.66,
      "analyst_target_high": 817.63,
      "analyst_target_low": 366.23,
      "52w_high": 763.96,
      "52w_low": 270.93,
      "timestamp": "2026-05-01T09:19:57.078642",
      "shares": 0,
      "value_eur": 0.0
    },
    {
      "ticker": "IBE.MC",
      "name": "ACCIONES IBERDROLA",
      "price_native": 19.95,
      "prev_close": 20.0,
      "currency": "EUR",
      "change_pct": -0.25,
      "price_eur": 19.95,
      "prev_eur": 20.0,
      "sector": "Utilities",
      "country": "Spain",
      "pe_ratio": 24.9375,
      "beta": 0.604,
      "eps_ttm": 0.8,
      "dividend_yield": 3.28,
      "market_cap": 134819020800,
      "pb_ratio": 2.6284585,
      "ps_ratio": 3.0587854,
      "roe": 0.10325,
      "roa": 0.039100002,
      "debt_to_equity": 93.674,
      "current_ratio": 0.874,
      "profit_margin": 0.14259,
      "revenue_growth": 0.005,
      "earnings_growth": 5.598,
      "recommendation": "hold",
      "analyst_total": 23,
      "analyst_target_mean": 19.22,
      "analyst_target_high": 22.2,
      "analyst_target_low": 14.5,
      "52w_high": 20.6,
      "52w_low": 15.03,
      "timestamp": "2026-05-01T09:19:57.592092",
      "shares": 0,
      "value_eur": 0.0
    },
    {
      "ticker": "SNDK",
      "name": "Sandisk Corporation",
      "price_native": 1096.51,
      "prev_close": 1031.0,
      "currency": "USD",
      "change_pct": 6.35,
      "price_eur": 933.9,
      "prev_eur": 878.1,
      "sector": "Technology",
      "country": "United States",
      "pe_ratio": 37.449112,
      "beta": null,
      "eps_ttm": 29.28,
      "dividend_yield": null,
      "market_cap": 161845952512,
      "pb_ratio": 15.889836,
      "ps_ratio": 12.275937,
      "roe": 0.39297,
      "roa": 0.22815001,
      "debt_to_equity": null,
      "current_ratio": 4.782,
      "profit_margin": 0.34185,
      "revenue_growth": 2.51,
      "earnings_growth": null,
      "recommendation": "buy",
      "analyst_total": 21,
      "analyst_target_mean": 895.3,
      "analyst_target_high": 1533.06,
      "analyst_target_low": 553.61,
      "52w_high": 949.65,
      "52w_low": 28.15,
      "timestamp": "2026-05-01T09:19:57.994514",
      "shares": 0,
      "value_eur": 0.0
    },
    {
      "ticker": "SMHN.DE",
      "name": "SUSS MicroTec SE              N",
      "price_native": 76.2,
      "prev_close": 69.65,
      "currency": "EUR",
      "change_pct": 9.4,
      "price_eur": 76.2,
      "prev_eur": 69.65,
      "sector": "Technology",
      "country": "Germany",
      "pe_ratio": 25.830507,
      "beta": 1.978,
      "eps_ttm": 2.95,
      "dividend_yield": 0.05,
      "market_cap": 1456603904,
      "pb_ratio": 4.6170626,
      "ps_ratio": 2.8947968,
      "roe": 0.16545999,
      "roa": 0.074939996,
      "debt_to_equity": 15.731,
      "current_ratio": 3.282,
      "profit_margin": 0.091630004,
      "revenue_growth": -0.215,
      "earnings_growth": -0.402,
      "recommendation": "buy",
      "analyst_total": 8,
      "analyst_target_mean": 61.38,
      "analyst_target_high": 70.0,
      "analyst_target_low": 37.0,
      "52w_high": 76.9,
      "52w_low": 24.0,
      "timestamp": "2026-05-01T09:19:58.371837",
      "shares": 0,
      "value_eur": 0.0
    },
    {
      "ticker": "ALV.DE",
      "name": "Allianz SE                    v",
      "price_native": 389.0,
      "prev_close": 384.9,
      "currency": "EUR",
      "change_pct": 1.07,
      "price_eur": 389.0,
      "prev_eur": 384.9,
      "sector": "Financial Services",
      "country": "Germany",
      "pe_ratio": 14.06363,
      "beta": 0.648,
      "eps_ttm": 27.66,
      "dividend_yield": 4.4,
      "market_cap": 147914211328,
      "pb_ratio": 2.3582475,
      "ps_ratio": 1.3069627,
      "roe": 0.17527,
      "roa": 0.01056,
      "debt_to_equity": 53.166,
      "current_ratio": 1.578,
      "profit_margin": 0.09521,
      "revenue_growth": -0.056,
      "earnings_growth": 0.095,
      "recommendation": "buy",
      "analyst_total": 18,
      "analyst_target_mean": 400.08,
      "analyst_target_high": 504.0,
      "analyst_target_low": 325.0,
      "52w_high": 397.0,
      "52w_low": 333.2,
      "timestamp": "2026-05-01T09:19:58.955199",
      "shares": 0,
      "value_eur": 0.0
    },
    {
      "ticker": "TTE.PA",
      "name": "TOTALENERGIES",
      "price_native": 79.29,
      "prev_close": 78.26,
      "currency": "EUR",
      "change_pct": 1.32,
      "price_eur": 79.29,
      "prev_eur": 78.26,
      "sector": "Energy",
      "country": "France",
      "pe_ratio": 13.789565,
      "beta": 0.064,
      "eps_ttm": 5.75,
      "dividend_yield": 4.54,
      "market_cap": 176537239552,
      "pb_ratio": 1.7449242,
      "ps_ratio": 0.959645,
      "roe": 0.12512,
      "roa": 0.04892,
      "debt_to_equity": 51.304,
      "current_ratio": 1.076,
      "profit_margin": 0.08201,
      "revenue_growth": 0.034,
      "earnings_growth": 0.571,
      "recommendation": "buy",
      "analyst_total": 21,
      "analyst_target_mean": 83.38,
      "analyst_target_high": 94.74,
      "analyst_target_low": 69.41,
      "52w_high": 81.34,
      "52w_low": 49.24,
      "timestamp": "2026-05-01T09:19:59.427202",
      "shares": 0,
      "value_eur": 0.0
    },
    {
      "ticker": "BP.L",
      "name": "BP PLC $0.25",
      "price_native": 583.9,
      "prev_close": 583.0,
      "currency": "GBX",
      "change_pct": 0.15,
      "price_eur": 6.76,
      "prev_eur": 6.75,
      "sector": "Energy",
      "country": "United Kingdom",
      "pe_ratio": 38.926666,
      "beta": -0.195,
      "eps_ttm": 0.15,
      "dividend_yield": 4.25,
      "market_cap": 90212466688,
      "pb_ratio": 2.2910755,
      "ps_ratio": 0.46741,
      "roe": 0.05842,
      "roa": 0.03961,
      "debt_to_equity": 96.384,
      "current_ratio": 1.219,
      "profit_margin": 0.01663,
      "revenue_growth": 0.116,
      "earnings_growth": 4.745,
      "recommendation": "buy",
      "analyst_total": 19,
      "analyst_target_mean": 7.15,
      "analyst_target_high": 8.11,
      "analyst_target_low": 5.29,
      "52w_high": 7.06,
      "52w_low": 3.99,
      "timestamp": "2026-05-01T09:19:59.859660",
      "shares": 0,
      "value_eur": 0.0
    },
    {
      "ticker": "INTC",
      "name": "Intel Corporation",
      "price_native": 94.48,
      "prev_close": 93.55,
      "currency": "USD",
      "change_pct": 0.99,
      "price_eur": 80.47,
      "prev_eur": 79.68,
      "sector": "Technology",
      "country": "United States",
      "pe_ratio": 63.81628,
      "beta": 1.349,
      "eps_ttm": -0.6,
      "dividend_yield": null,
      "market_cap": 474856488960,
      "pb_ratio": 4.1286488,
      "ps_ratio": 8.832403,
      "roe": -0.02911,
      "roa": 0.0063099996,
      "debt_to_equity": 36.028,
      "current_ratio": 2.312,
      "profit_margin": -0.05904,
      "revenue_growth": 0.072,
      "earnings_growth": null,
      "recommendation": "hold",
      "analyst_total": 42,
      "analyst_target_mean": 65.56,
      "analyst_target_high": 95.39,
      "analyst_target_low": 17.37,
      "52w_high": 81.5,
      "52w_low": 16.16,
      "timestamp": "2026-05-01T09:20:00.314963",
      "shares": 0,
      "value_eur": 0.0
    },
    {
      "ticker": "AMD",
      "name": "Advanced Micro Devices, Inc.",
      "price_native": 354.49,
      "prev_close": 351.4,
      "currency": "USD",
      "change_pct": 0.88,
      "price_eur": 301.92,
      "prev_eur": 299.29,
      "sector": "Technology",
      "country": "United States",
      "pe_ratio": 135.30153,
      "beta": 1.963,
      "eps_ttm": 2.62,
      "dividend_yield": null,
      "market_cap": 577964343296,
      "pb_ratio": 9.171798,
      "ps_ratio": 16.685366,
      "roe": 0.07082,
      "roa": 0.032,
      "debt_to_equity": 6.359,
      "current_ratio": 2.85,
      "profit_margin": 0.12515001,
      "revenue_growth": 0.341,
      "earnings_growth": 2.171,
      "recommendation": "buy",
      "analyst_total": 46,
      "analyst_target_mean": 255.97,
      "analyst_target_high": 387.52,
      "analyst_target_low": 191.63,
      "52w_high": 302.32,
      "52w_low": 82.51,
      "timestamp": "2026-05-01T09:20:00.638223",
      "shares": 0,
      "value_eur": 0.0
    },
    {
      "ticker": "TXN",
      "name": "Texas Instruments Incorporated",
      "price_native": 281.08,
      "prev_close": 281.0,
      "currency": "USD",
      "change_pct": 0.03,
      "price_eur": 239.4,
      "prev_eur": 239.33,
      "sector": "Technology",
      "country": "United States",
      "pe_ratio": 48.047863,
      "beta": 0.994,
      "eps_ttm": 5.85,
      "dividend_yield": 2.02,
      "market_cap": 255808864256,
      "pb_ratio": 15.245429,
      "ps_ratio": 13.874002,
      "roe": 0.32347,
      "roa": 0.12161,
      "debt_to_equity": 83.741,
      "current_ratio": 4.456,
      "profit_margin": 0.29108,
      "revenue_growth": 0.186,
      "earnings_growth": 0.313,
      "recommendation": "buy",
      "analyst_total": 32,
      "analyst_target_mean": 234.16,
      "analyst_target_high": 281.06,
      "analyst_target_low": 170.34,
      "52w_high": 245.14,
      "52w_low": 130.08,
      "timestamp": "2026-05-01T09:20:01.111225",
      "shares": 0,
      "value_eur": 0.0
    },
    {
      "ticker": "ASML",
      "name": "ASML Holding N.V. - New York Re",
      "price_native": 1438.99,
      "prev_close": 1435.0,
      "currency": "USD",
      "change_pct": 0.28,
      "price_eur": 1225.59,
      "prev_eur": 1222.19,
      "sector": "Technology",
      "country": "Netherlands",
      "pe_ratio": 47.39756,
      "beta": 1.382,
      "eps_ttm": 30.36,
      "dividend_yield": 0.61,
      "market_cap": 554612162560,
      "pb_ratio": 1255.2676,
      "ps_ratio": 16.4609,
      "roe": 0.52236,
      "roa": 0.15664,
      "debt_to_equity": 12.989,
      "current_ratio": 1.36,
      "profit_margin": 0.29713,
      "revenue_growth": 0.132,
      "earnings_growth": 0.192,
      "recommendation": "buy",
      "analyst_total": 15,
      "analyst_target_mean": 1417.41,
      "analyst_target_high": 1706.6,
      "analyst_target_low": 773.64,
      "52w_high": 1317.77,
      "52w_low": 575.32,
      "timestamp": "2026-05-01T09:20:01.523911",
      "shares": 0,
      "value_eur": 0.0
    },
    {
      "ticker": "STMPA.PA",
      "name": "STMICROELECTRONICS",
      "price_native": 46.015,
      "prev_close": 44.7,
      "currency": "EUR",
      "change_pct": 2.94,
      "price_eur": 46.01,
      "prev_eur": 44.7,
      "sector": "Technology",
      "country": "Netherlands",
      "pe_ratio": 328.67856,
      "beta": 1.218,
      "eps_ttm": 0.14,
      "dividend_yield": 0.68,
      "market_cap": 40897859584,
      "pb_ratio": 2.654918,
      "ps_ratio": 3.3040764,
      "roe": 0.00908,
      "roa": 0.01563,
      "debt_to_equity": 14.138,
      "current_ratio": 3.313,
      "profit_margin": 0.011879999,
      "revenue_growth": 0.23,
      "earnings_growth": -0.333,
      "recommendation": "buy",
      "analyst_total": 21,
      "analyst_target_mean": 45.26,
      "analyst_target_high": 52.84,
      "analyst_target_low": 28.46,
      "52w_high": 46.02,
      "52w_low": 18.2,
      "timestamp": "2026-05-01T09:20:01.995530",
      "shares": 0,
      "value_eur": 0.0
    },
    {
      "ticker": "SU.PA",
      "name": "SCHNEIDER ELECTRIC SE",
      "price_native": 268.6,
      "prev_close": 271.05,
      "currency": "EUR",
      "change_pct": -0.9,
      "price_eur": 268.6,
      "prev_eur": 271.05,
      "sector": "Industrials",
      "country": "France",
      "pe_ratio": 33.65915,
      "beta": 1.095,
      "eps_ttm": 7.98,
      "dividend_yield": 1.56,
      "market_cap": 150894854144,
      "pb_ratio": 6.2404165,
      "ps_ratio": 3.7580907,
      "roe": 0.15613,
      "roa": 0.0678,
      "debt_to_equity": 81.411,
      "current_ratio": 1.191,
      "profit_margin": 0.10368,
      "revenue_growth": 0.042,
      "earnings_growth": -0.062,
      "recommendation": "buy",
      "analyst_total": 22,
      "analyst_target_mean": 296.5,
      "analyst_target_high": 340.0,
      "analyst_target_low": 250.0,
      "52w_high": 281.5,
      "52w_low": 208.8,
      "timestamp": "2026-05-01T09:20:02.516508",
      "shares": 0,
      "value_eur": 0.0
    },
    {
      "ticker": "NOK",
      "name": "Nokia Corporation Sponsored",
      "price_native": 12.91,
      "prev_close": 12.9506,
      "currency": "USD",
      "change_pct": -0.31,
      "price_eur": 11.0,
      "prev_eur": 11.03,
      "sector": "Technology",
      "country": "Finland",
      "pe_ratio": 80.6875,
      "beta": 0.513,
      "eps_ttm": 0.16,
      "dividend_yield": 1.27,
      "market_cap": 72070512640,
      "pb_ratio": 2.9698853,
      "ps_ratio": 3.6042464,
      "roe": 0.037249997,
      "roa": 0.027560001,
      "debt_to_equity": 15.63,
      "current_ratio": 1.567,
      "profit_margin": 0.039809998,
      "revenue_growth": 0.024,
      "earnings_growth": null,
      "recommendation": "buy",
      "analyst_total": 9,
      "analyst_target_mean": 10.0,
      "analyst_target_high": 12.78,
      "analyst_target_low": 6.47,
      "52w_high": 11.0,
      "52w_low": 3.41,
      "timestamp": "2026-05-01T09:20:03.014959",
      "shares": 0,
      "value_eur": 0.0
    },
    {
      "ticker": "HSBA.L",
      "name": "HSBC HOLDINGS PLC ORD $0.50 (UK",
      "price_native": 1338.953,
      "prev_close": 1348.6,
      "currency": "GBX",
      "change_pct": -0.72,
      "price_eur": 15.51,
      "prev_eur": 15.62,
      "sector": "Financial Services",
      "country": "United Kingdom",
      "pe_ratio": 15.044416,
      "beta": 0.555,
      "eps_ttm": 0.89,
      "dividend_yield": 4.12,
      "market_cap": 229606227968,
      "pb_ratio": 1.7493662,
      "ps_ratio": 3.631631,
      "roe": 0.11625,
      "roa": 0.0074,
      "debt_to_equity": null,
      "current_ratio": null,
      "profit_margin": 0.35248002,
      "revenue_growth": 0.584,
      "earnings_growth": 23.979,
      "recommendation": "buy",
      "analyst_total": 17,
      "analyst_target_mean": 15.69,
      "analyst_target_high": 18.86,
      "analyst_target_low": 8.98,
      "52w_high": 16.34,
      "52w_low": 9.61,
      "timestamp": "2026-05-01T09:20:03.480841",
      "shares": 0,
      "value_eur": 0.0
    },
    {
      "ticker": "SMSN.L",
      "name": "Samsung Electronics Co., Ltd.",
      "price_native": 1179.5,
      "prev_close": 1179.5,
      "currency": "USD",
      "change_pct": 0.0,
      "price_eur": 1004.58,
      "prev_eur": 1004.58,
      "sector": "Technology",
      "country": "South Korea",
      "pe_ratio": 10.5359535,
      "beta": 1.211,
      "eps_ttm": 111.95,
      "dividend_yield": 0.77,
      "market_cap": 309810462720,
      "pb_ratio": 1.081271,
      "ps_ratio": 0.00092867186,
      "roe": 0.10783,
      "roa": 0.0504,
      "debt_to_equity": 5.785,
      "current_ratio": 2.328,
      "profit_margin": 0.13267,
      "revenue_growth": 0.238,
      "earnings_growth": 1.622,
      "recommendation": "hold",
      "analyst_total": 5,
      "analyst_target_mean": 3647.72,
      "analyst_target_high": 4968.25,
      "analyst_target_low": 2080.7,
      "52w_high": 2781.65,
      "52w_low": 753.75,
      "timestamp": "2026-05-01T09:20:04.035929",
      "shares": 0,
      "value_eur": 0.0
    },
    {
      "ticker": "AVGO",
      "name": "Broadcom Inc.",
      "price_native": 417.43,
      "prev_close": 414.39,
      "currency": "USD",
      "change_pct": 0.73,
      "price_eur": 355.53,
      "prev_eur": 352.94,
      "sector": "Technology",
      "country": "United States",
      "pe_ratio": 81.37037,
      "beta": 1.253,
      "eps_ttm": 5.13,
      "dividend_yield": 0.62,
      "market_cap": 1976392613888,
      "pb_ratio": 24.75126,
      "ps_ratio": 28.944563,
      "roe": 0.33370999,
      "roa": 0.10663,
      "debt_to_equity": 82.704,
      "current_ratio": 1.902,
      "profit_margin": 0.36571997,
      "revenue_growth": 0.295,
      "earnings_growth": 0.316,
      "recommendation": "buy",
      "analyst_total": 42,
      "analyst_target_mean": 404.98,
      "analyst_target_high": 536.57,
      "analyst_target_low": 306.61,
      "52w_high": 365.64,
      "52w_low": 166.88,
      "timestamp": "2026-05-01T09:20:04.635114",
      "shares": 0,
      "value_eur": 0.0
    },
    {
      "ticker": "MRVL",
      "name": "Marvell Technology, Inc.",
      "price_native": 165.15,
      "prev_close": 163.36,
      "currency": "USD",
      "change_pct": 1.1,
      "price_eur": 140.66,
      "prev_eur": 139.13,
      "sector": "Technology",
      "country": "United States",
      "pe_ratio": 53.79479,
      "beta": 1.822,
      "eps_ttm": 3.07,
      "dividend_yield": 0.15,
      "market_cap": 144416768000,
      "pb_ratio": 9.779713,
      "ps_ratio": 17.623407,
      "roe": 0.19253999,
      "roa": 0.039389998,
      "debt_to_equity": 33.479,
      "current_ratio": 2.006,
      "profit_margin": 0.32584,
      "revenue_growth": 0.221,
      "earnings_growth": 1.063,
      "recommendation": "buy",
      "analyst_total": 39,
      "analyst_target_mean": 109.32,
      "analyst_target_high": 144.79,
      "analyst_target_low": 72.39,
      "52w_high": 145.5,
      "52w_low": 45.8,
      "timestamp": "2026-05-01T09:20:04.933890",
      "shares": 0,
      "value_eur": 0.0
    }
  ],
  "etfs": [
    {
      "ticker": "SPYY.DE",
      "name": "SPDR MSCI ACW UCITS ETF       R",
      "price_native": 261.9,
      "prev_close": 260.45,
      "currency": "EUR",
      "change_pct": 0.56,
      "price_eur": 261.9,
      "prev_eur": 260.45,
      "sector": "",
      "country": "",
      "pe_ratio": null,
      "beta": null,
      "eps_ttm": null,
      "dividend_yield": null,
      "market_cap": null,
      "pb_ratio": null,
      "ps_ratio": null,
      "roe": null,
      "roa": null,
      "debt_to_equity": null,
      "current_ratio": null,
      "profit_margin": null,
      "revenue_growth": null,
      "earnings_growth": null,
      "analyst_total": 0,
      "52w_high": 262.65,
      "52w_low": 208.45,
      "timestamp": "2026-05-01T09:20:05.230787",
      "shares": 30,
      "value_eur": 7857.0,
      "holdings": [
        {
          "ticker": "US67066G1040",
          "name": "NVIDIA Corporation",
          "weight_pct": 4.9135
        },
        {
          "ticker": "US0378331005",
          "name": "Apple Inc.",
          "weight_pct": 4.0434
        },
        {
          "ticker": "US5949181045",
          "name": "Microsoft Corporation",
          "weight_pct": 2.902
        },
        {
          "ticker": "US0231351067",
          "name": "Amazon.com Inc.",
          "weight_pct": 2.557
        },
        {
          "ticker": "US02079K3059",
          "name": "Alphabet Inc. Class A",
          "weight_pct": 2.2379
        },
        {
          "ticker": "US11135F1012",
          "name": "Broadcom Inc.",
          "weight_pct": 1.8994
        },
        {
          "ticker": "US02079K1079",
          "name": "Alphabet Inc. Class C",
          "weight_pct": 1.8861
        },
        {
          "ticker": "TW0002330008",
          "name": "Taiwan Semiconductor Manufacturing Co. L",
          "weight_pct": 1.676
        },
        {
          "ticker": "US30303M1027",
          "name": "Meta Platforms Inc Class A",
          "weight_pct": 1.3537
        },
        {
          "ticker": "US88160R1014",
          "name": "Tesla Inc.",
          "weight_pct": 1.093
        },
        {
          "ticker": "US46625H1005",
          "name": "JPMorgan Chase & Co.",
          "weight_pct": 0.8566
        },
        {
          "ticker": "US5324571083",
          "name": "Eli Lilly and Company",
          "weight_pct": 0.7763
        },
        {
          "ticker": "KR7005930003",
          "name": "Samsung Electronics Co. Ltd.",
          "weight_pct": 0.7253
        },
        {
          "ticker": "US30231G1022",
          "name": "Exxon Mobil Corporation",
          "weight_pct": 0.6621
        },
        {
          "ticker": "US0846707026",
          "name": "Berkshire Hathaway Inc. Class B",
          "weight_pct": 0.6368
        },
        {
          "ticker": "US0079031078",
          "name": "Advanced Micro Devices Inc.",
          "weight_pct": 0.5964
        },
        {
          "ticker": "NL0010273215",
          "name": "ASML Holding NV",
          "weight_pct": 0.5829
        },
        {
          "ticker": "US9311421039",
          "name": "Walmart Inc.",
          "weight_pct": 0.5824
        },
        {
          "ticker": "US5951121038",
          "name": "Micron Technology Inc.",
          "weight_pct": 0.5806
        },
        {
          "ticker": "US92826C8394",
          "name": "Visa Inc. Class A",
          "weight_pct": 0.5517
        },
        {
          "ticker": "US4781601046",
          "name": "Johnson & Johnson",
          "weight_pct": 0.537
        },
        {
          "ticker": "KR7000660001",
          "name": "SK hynix Inc.",
          "weight_pct": 0.4868
        },
        {
          "ticker": "US22160K1051",
          "name": "Costco Wholesale Corporation",
          "weight_pct": 0.4551
        },
        {
          "ticker": "US4581401001",
          "name": "Intel Corporation",
          "weight_pct": 0.4387
        },
        {
          "ticker": "US57636Q1040",
          "name": "Mastercard Incorporated Class A",
          "weight_pct": 0.4141
        }
      ]
    },
    {
      "ticker": "EUNK.DE",
      "name": "iShsIII-C.MSCI Eu.U.E.EUR Acc R",
      "price_native": 97.8,
      "prev_close": 96.38,
      "currency": "EUR",
      "change_pct": 1.47,
      "price_eur": 97.8,
      "prev_eur": 96.38,
      "sector": "",
      "country": "",
      "pe_ratio": 18.718636,
      "beta": null,
      "eps_ttm": null,
      "dividend_yield": null,
      "market_cap": null,
      "pb_ratio": null,
      "ps_ratio": null,
      "roe": null,
      "roa": null,
      "debt_to_equity": null,
      "current_ratio": null,
      "profit_margin": null,
      "revenue_growth": null,
      "earnings_growth": null,
      "analyst_total": 0,
      "52w_high": 101.1,
      "52w_low": 83.12,
      "timestamp": "2026-05-01T09:20:07.148472",
      "shares": 20,
      "value_eur": 1956.0,
      "holdings": [
        {
          "ticker": "ASML",
          "name": "ASML HOLDING NV",
          "weight_pct": 3.9
        },
        {
          "ticker": "HSBA",
          "name": "HSBC HOLDINGS PLC",
          "weight_pct": 2.22
        },
        {
          "ticker": "AZN",
          "name": "ASTRAZENECA PLC",
          "weight_pct": 2.07
        },
        {
          "ticker": "ROP",
          "name": "ROCHE PS PAR AG",
          "weight_pct": 2.03
        },
        {
          "ticker": "NOVN",
          "name": "NOVARTIS AG",
          "weight_pct": 1.97
        },
        {
          "ticker": "NESN",
          "name": "NESTLE SA",
          "weight_pct": 1.86
        },
        {
          "ticker": "SHEL",
          "name": "SHELL PLC",
          "weight_pct": 1.82
        },
        {
          "ticker": "SIE",
          "name": "SIEMENS N AG",
          "weight_pct": 1.58
        },
        {
          "ticker": "TTE",
          "name": "TOTALENERGIES",
          "weight_pct": 1.31
        },
        {
          "ticker": "SAN",
          "name": "BANCO SANTANDER SA",
          "weight_pct": 1.3
        },
        {
          "ticker": "SAP",
          "name": "SAP",
          "weight_pct": 1.28
        },
        {
          "ticker": "SU",
          "name": "SCHNEIDER ELECTRIC",
          "weight_pct": 1.26
        },
        {
          "ticker": "ALV",
          "name": "ALLIANZ",
          "weight_pct": 1.24
        },
        {
          "ticker": "ENR",
          "name": "SIEMENS ENERGY N AG",
          "weight_pct": 1.15
        },
        {
          "ticker": "ABBN",
          "name": "ABB LTD",
          "weight_pct": 1.1
        },
        {
          "ticker": "IBE",
          "name": "IBERDROLA SA",
          "weight_pct": 1.08
        },
        {
          "ticker": "UBSG",
          "name": "UBS GROUP AG",
          "weight_pct": 0.99
        },
        {
          "ticker": "MC",
          "name": "LVMH",
          "weight_pct": 0.94
        },
        {
          "ticker": "NOVO B",
          "name": "NOVO NORDISK CLASS B",
          "weight_pct": 0.93
        },
        {
          "ticker": "BATS",
          "name": "BRITISH AMERICAN TOBACCO",
          "weight_pct": 0.9
        },
        {
          "ticker": "RR.",
          "name": "ROLLS-ROYCE HOLDINGS PLC",
          "weight_pct": 0.9
        },
        {
          "ticker": "ULVR",
          "name": "UNILEVER PLC",
          "weight_pct": 0.89
        },
        {
          "ticker": "BBVA",
          "name": "BANCO BILBAO VIZCAYA ARGENTARIA SA",
          "weight_pct": 0.89
        },
        {
          "ticker": "AI",
          "name": "LAIR LIQUIDE SOCIETE ANONYME POUR",
          "weight_pct": 0.88
        },
        {
          "ticker": "BP.",
          "name": "BP PLC",
          "weight_pct": 0.88
        }
      ]
    },
    {
      "ticker": "IS3N.DE",
      "name": "iShs Core MSCI EM IMI U.ETF   R",
      "price_native": 44.298,
      "prev_close": 44.036,
      "currency": "EUR",
      "change_pct": 0.59,
      "price_eur": 44.3,
      "prev_eur": 44.04,
      "sector": "",
      "country": "",
      "pe_ratio": null,
      "beta": null,
      "eps_ttm": null,
      "dividend_yield": null,
      "market_cap": null,
      "pb_ratio": null,
      "ps_ratio": null,
      "roe": null,
      "roa": null,
      "debt_to_equity": null,
      "current_ratio": null,
      "profit_margin": null,
      "revenue_growth": null,
      "earnings_growth": null,
      "analyst_total": 0,
      "52w_high": 44.59,
      "52w_low": 31.69,
      "timestamp": "2026-05-01T09:20:08.453781",
      "shares": 10,
      "value_eur": 443.0,
      "holdings": [
        {
          "ticker": "2330",
          "name": "TAIWAN SEMICONDUCTOR MANUFACTURING",
          "weight_pct": 12.48
        },
        {
          "ticker": "005930",
          "name": "SAMSUNG ELECTRONICS LTD",
          "weight_pct": 5.31
        },
        {
          "ticker": "000660",
          "name": "SK HYNIX INC",
          "weight_pct": 3.49
        },
        {
          "ticker": "700",
          "name": "TENCENT HOLDINGS LTD",
          "weight_pct": 2.86
        },
        {
          "ticker": "9988",
          "name": "ALIBABA GROUP HOLDING LTD",
          "weight_pct": 2.1
        },
        {
          "ticker": "2308",
          "name": "DELTA ELECTRONICS INC",
          "weight_pct": 0.98
        },
        {
          "ticker": "2454",
          "name": "MEDIATEK INC",
          "weight_pct": 0.91
        },
        {
          "ticker": "939",
          "name": "CHINA CONSTRUCTION BANK CORP H",
          "weight_pct": 0.81
        },
        {
          "ticker": "HDFCBANK",
          "name": "HDFC BANK LTD",
          "weight_pct": 0.69
        },
        {
          "ticker": "005935",
          "name": "SAMSUNG ELECTRONICS NON VOTING PRE",
          "weight_pct": 0.66
        },
        {
          "ticker": "RELIANCE",
          "name": "RELIANCE INDUSTRIES LTD",
          "weight_pct": 0.66
        },
        {
          "ticker": "2317",
          "name": "HON HAI PRECISION INDUSTRY LTD",
          "weight_pct": 0.66
        },
        {
          "ticker": "ICICIBANK",
          "name": "ICICI BANK LTD",
          "weight_pct": 0.52
        },
        {
          "ticker": "4BRZ",
          "name": "ISHARES MSCI BRAZIL UCITS ET USDHA",
          "weight_pct": 0.52
        },
        {
          "ticker": "PDD",
          "name": "PDD HOLDINGS ADS INC",
          "weight_pct": 0.51
        },
        {
          "ticker": "1810",
          "name": "XIAOMI CORP",
          "weight_pct": 0.48
        },
        {
          "ticker": "1398",
          "name": "INDUSTRIAL AND COMMERCIAL BANK OF",
          "weight_pct": 0.44
        },
        {
          "ticker": "2318",
          "name": "PING AN INSURANCE (GROUP) CO OF CH",
          "weight_pct": 0.4
        },
        {
          "ticker": "3690",
          "name": "MEITUAN",
          "weight_pct": 0.39
        },
        {
          "ticker": "402340",
          "name": "SK SQUARE LTD",
          "weight_pct": 0.38
        },
        {
          "ticker": "BHARTIARTL",
          "name": "BHARTI AIRTEL LTD",
          "weight_pct": 0.37
        },
        {
          "ticker": "3711",
          "name": "ASE TECHNOLOGY HOLDING LTD",
          "weight_pct": 0.37
        },
        {
          "ticker": "1211",
          "name": "BYD LTD H",
          "weight_pct": 0.37
        },
        {
          "ticker": "1120",
          "name": "AL RAJHI BANK",
          "weight_pct": 0.36
        },
        {
          "ticker": "005380",
          "name": "HYUNDAI MOTOR",
          "weight_pct": 0.36
        }
      ]
    },
    {
      "ticker": "SEMI.AS",
      "name": "iShares MSCI Global Semiconduct",
      "price_native": 16.822,
      "prev_close": 16.456,
      "currency": "USD",
      "change_pct": 2.22,
      "price_eur": 14.33,
      "prev_eur": 14.02,
      "sector": "",
      "country": "",
      "pe_ratio": 44.60131,
      "beta": null,
      "eps_ttm": null,
      "dividend_yield": 0.0,
      "market_cap": null,
      "pb_ratio": null,
      "ps_ratio": null,
      "roe": null,
      "roa": null,
      "debt_to_equity": null,
      "current_ratio": null,
      "profit_margin": null,
      "revenue_growth": null,
      "earnings_growth": null,
      "analyst_total": 0,
      "52w_high": 14.53,
      "52w_low": 5.45,
      "timestamp": "2026-05-01T09:20:09.990466",
      "shares": 0,
      "value_eur": 0.0,
      "holdings": [
        {
          "ticker": "MU",
          "name": "MICRON TECHNOLOGY INC",
          "weight_pct": 7.83
        },
        {
          "ticker": "AVGO",
          "name": "BROADCOM INC",
          "weight_pct": 7.36
        },
        {
          "ticker": "2330",
          "name": "TAIWAN SEMICONDUCTOR MANUFACTURING",
          "weight_pct": 6.87
        },
        {
          "ticker": "NVDA",
          "name": "NVIDIA CORP",
          "weight_pct": 6.83
        },
        {
          "ticker": "AMD",
          "name": "ADVANCED MICRO DEVICES INC",
          "weight_pct": 6.02
        },
        {
          "ticker": "ASML",
          "name": "ASML HOLDING NV",
          "weight_pct": 5.95
        },
        {
          "ticker": "INTC",
          "name": "INTEL CORPORATION CORP",
          "weight_pct": 5.95
        },
        {
          "ticker": "000660",
          "name": "SK HYNIX INC",
          "weight_pct": 5.21
        },
        {
          "ticker": "AMAT",
          "name": "APPLIED MATERIAL INC",
          "weight_pct": 3.86
        },
        {
          "ticker": "LRCX",
          "name": "LAM RESEARCH CORP",
          "weight_pct": 3.81
        },
        {
          "ticker": "TXN",
          "name": "TEXAS INSTRUMENT INC",
          "weight_pct": 3.4
        },
        {
          "ticker": "KLAC",
          "name": "KLA CORP",
          "weight_pct": 3.31
        },
        {
          "ticker": "ADI",
          "name": "ANALOG DEVICES INC",
          "weight_pct": 2.65
        },
        {
          "ticker": "QCOM",
          "name": "QUALCOMM INC",
          "weight_pct": 2.31
        },
        {
          "ticker": "6857",
          "name": "ADVANTEST CORP",
          "weight_pct": 1.97
        },
        {
          "ticker": "MRVL",
          "name": "MARVELL TECHNOLOGY INC",
          "weight_pct": 1.84
        },
        {
          "ticker": "8035",
          "name": "TOKYO ELECTRON LTD",
          "weight_pct": 1.75
        },
        {
          "ticker": "2454",
          "name": "MEDIATEK INC",
          "weight_pct": 1.72
        },
        {
          "ticker": "IFX",
          "name": "INFINEON TECHNOLOGIES AG",
          "weight_pct": 1.19
        },
        {
          "ticker": "MPWR",
          "name": "MONOLITHIC POWER SYSTEMS INC",
          "weight_pct": 1.02
        },
        {
          "ticker": "NXPI",
          "name": "NXP SEMICONDUCTORS NV",
          "weight_pct": 1.01
        },
        {
          "ticker": "3711",
          "name": "ASE TECHNOLOGY HOLDING LTD",
          "weight_pct": 0.72
        },
        {
          "ticker": "MCHP",
          "name": "MICROCHIP TECHNOLOGY INC",
          "weight_pct": 0.68
        },
        {
          "ticker": "TER",
          "name": "TERADYNE INC",
          "weight_pct": 0.67
        },
        {
          "ticker": "ASM",
          "name": "ASM INTERNATIONAL NV",
          "weight_pct": 0.62
        }
      ]
    },
    {
      "ticker": "QDVE.DE",
      "name": "iShsV-S&P 500 Inf.Te.Sec.U.ETFR",
      "price_native": 37.895,
      "prev_close": 38.4,
      "currency": "EUR",
      "change_pct": -1.32,
      "price_eur": 37.9,
      "prev_eur": 38.4,
      "sector": "",
      "country": "",
      "pe_ratio": null,
      "beta": null,
      "eps_ttm": null,
      "dividend_yield": null,
      "market_cap": null,
      "pb_ratio": null,
      "ps_ratio": null,
      "roe": null,
      "roa": null,
      "debt_to_equity": null,
      "current_ratio": null,
      "profit_margin": null,
      "revenue_growth": null,
      "earnings_growth": null,
      "analyst_total": 0,
      "52w_high": 38.69,
      "52w_low": 26.65,
      "timestamp": "2026-05-01T09:20:11.093109",
      "shares": 10,
      "value_eur": 379.0,
      "holdings": [
        {
          "ticker": "NVDA",
          "name": "NVIDIA CORP",
          "weight_pct": 23.31
        },
        {
          "ticker": "AAPL",
          "name": "APPLE INC",
          "weight_pct": 16.66
        },
        {
          "ticker": "MSFT",
          "name": "MICROSOFT CORP",
          "weight_pct": 14.87
        },
        {
          "ticker": "AVGO",
          "name": "BROADCOM INC",
          "weight_pct": 9.07
        },
        {
          "ticker": "MU",
          "name": "MICRON TECHNOLOGY INC",
          "weight_pct": 2.75
        },
        {
          "ticker": "AMD",
          "name": "ADVANCED MICRO DEVICES INC",
          "weight_pct": 2.59
        },
        {
          "ticker": "INTC",
          "name": "INTEL CORPORATION CORP",
          "weight_pct": 2.1
        },
        {
          "ticker": "CSCO",
          "name": "CISCO SYSTEMS INC",
          "weight_pct": 1.67
        },
        {
          "ticker": "PLTR",
          "name": "PALANTIR TECHNOLOGIES INC CLASS A",
          "weight_pct": 1.49
        },
        {
          "ticker": "LRCX",
          "name": "LAM RESEARCH CORP",
          "weight_pct": 1.47
        },
        {
          "ticker": "AMAT",
          "name": "APPLIED MATERIAL INC",
          "weight_pct": 1.43
        },
        {
          "ticker": "ORCL",
          "name": "ORACLE CORP",
          "weight_pct": 1.31
        },
        {
          "ticker": "TXN",
          "name": "TEXAS INSTRUMENT INC",
          "weight_pct": 1.15
        },
        {
          "ticker": "KLAC",
          "name": "KLA CORP",
          "weight_pct": 1.12
        },
        {
          "ticker": "IBM",
          "name": "INTERNATIONAL BUSINESS MACHINES CO",
          "weight_pct": 1.0
        },
        {
          "ticker": "ADI",
          "name": "ANALOG DEVICES INC",
          "weight_pct": 0.9
        },
        {
          "ticker": "APH",
          "name": "AMPHENOL CORP CLASS A",
          "weight_pct": 0.86
        },
        {
          "ticker": "ANET",
          "name": "ARISTA NETWORKS INC",
          "weight_pct": 0.82
        },
        {
          "ticker": "CRM",
          "name": "SALESFORCE INC",
          "weight_pct": 0.8
        },
        {
          "ticker": "QCOM",
          "name": "QUALCOMM INC",
          "weight_pct": 0.79
        },
        {
          "ticker": "SNDK",
          "name": "SANDISK CORP",
          "weight_pct": 0.74
        },
        {
          "ticker": "PANW",
          "name": "PALO ALTO NETWORKS INC",
          "weight_pct": 0.69
        },
        {
          "ticker": "STX",
          "name": "SEAGATE TECHNOLOGY HOLDINGS PLC",
          "weight_pct": 0.66
        },
        {
          "ticker": "WDC",
          "name": "WESTERN DIGITAL CORP",
          "weight_pct": 0.66
        },
        {
          "ticker": "APP",
          "name": "APPLOVIN CORP CLASS A",
          "weight_pct": 0.57
        }
      ]
    },
    {
      "ticker": "SXRV.DE",
      "name": "iShsVII-NASDAQ 100 UCITS ETF  R",
      "price_native": 1334.2,
      "prev_close": 1333.4,
      "currency": "EUR",
      "change_pct": 0.06,
      "price_eur": 1334.2,
      "prev_eur": 1333.4,
      "sector": "",
      "country": "",
      "pe_ratio": null,
      "beta": null,
      "eps_ttm": null,
      "dividend_yield": null,
      "market_cap": null,
      "pb_ratio": null,
      "ps_ratio": null,
      "roe": null,
      "roa": null,
      "debt_to_equity": null,
      "current_ratio": null,
      "profit_margin": null,
      "revenue_growth": null,
      "earnings_growth": null,
      "analyst_total": 0,
      "52w_high": 1346.2,
      "52w_low": 991.0,
      "timestamp": "2026-05-01T09:20:11.874318",
      "shares": 0,
      "value_eur": 0.0,
      "holdings": [
        {
          "ticker": "NVDA",
          "name": "NVIDIA CORP",
          "weight_pct": 9.04
        },
        {
          "ticker": "AAPL",
          "name": "APPLE INC",
          "weight_pct": 7.05
        },
        {
          "ticker": "MSFT",
          "name": "MICROSOFT CORP",
          "weight_pct": 5.6
        },
        {
          "ticker": "AMZN",
          "name": "AMAZON.COM INC",
          "weight_pct": 5.02
        },
        {
          "ticker": "GOOGL",
          "name": "ALPHABET INC CLASS A",
          "weight_pct": 3.62
        },
        {
          "ticker": "META",
          "name": "META PLATFORMS INC CLASS A",
          "weight_pct": 3.51
        },
        {
          "ticker": "AVGO",
          "name": "BROADCOM INC",
          "weight_pct": 3.42
        },
        {
          "ticker": "GOOG",
          "name": "ALPHABET INC CLASS C",
          "weight_pct": 3.36
        },
        {
          "ticker": "TSLA",
          "name": "TESLA INC",
          "weight_pct": 3.31
        },
        {
          "ticker": "WMT",
          "name": "WALMART INC",
          "weight_pct": 3.07
        },
        {
          "ticker": "MU",
          "name": "MICRON TECHNOLOGY INC",
          "weight_pct": 2.86
        },
        {
          "ticker": "AMD",
          "name": "ADVANCED MICRO DEVICES INC",
          "weight_pct": 2.7
        },
        {
          "ticker": "INTC",
          "name": "INTEL CORPORATION CORP",
          "weight_pct": 2.32
        },
        {
          "ticker": "COST",
          "name": "COSTCO WHOLESALE CORP",
          "weight_pct": 2.18
        },
        {
          "ticker": "NFLX",
          "name": "NETFLIX INC",
          "weight_pct": 1.91
        },
        {
          "ticker": "CSCO",
          "name": "CISCO SYSTEMS INC",
          "weight_pct": 1.74
        },
        {
          "ticker": "PLTR",
          "name": "PALANTIR TECHNOLOGIES INC CLASS A",
          "weight_pct": 1.55
        },
        {
          "ticker": "LRCX",
          "name": "LAM RESEARCH CORP",
          "weight_pct": 1.52
        },
        {
          "ticker": "AMAT",
          "name": "APPLIED MATERIAL INC",
          "weight_pct": 1.49
        },
        {
          "ticker": "TXN",
          "name": "TEXAS INSTRUMENT INC",
          "weight_pct": 1.2
        },
        {
          "ticker": "KLAC",
          "name": "KLA CORP",
          "weight_pct": 1.17
        },
        {
          "ticker": "LIN",
          "name": "LINDE PLC",
          "weight_pct": 1.15
        },
        {
          "ticker": "TMUS",
          "name": "T MOBILE US INC",
          "weight_pct": 1.07
        },
        {
          "ticker": "PEP",
          "name": "PEPSICO INC",
          "weight_pct": 1.04
        },
        {
          "ticker": "ADI",
          "name": "ANALOG DEVICES INC",
          "weight_pct": 0.93
        }
      ]
    }
  ],
  "total_eur": 18067.25,
  "timestamp": "2026-05-01T09:19:48.618054"
}